scienceworld/__init__.py
scienceworld/constants.py
scienceworld/object_type_ids.tsv
scienceworld/scienceworld.jar
scienceworld/scienceworld.py
scienceworld/tasks.json
scienceworld/utils.py
scienceworld/version.py
scienceworld-1.2.2.dist-info/LICENSE
scienceworld-1.2.2.dist-info/METADATA
scienceworld-1.2.2.dist-info/WHEEL
scienceworld-1.2.2.dist-info/top_level.txt
scienceworld-1.2.2.dist-info/RECORD
