Metadata-Version: 2.1
Name: scienceworld
Version: 1.2.2
Summary: ScienceWorld: An interactive text environment to study AIagents on accomplishing tasks from the standardized elementary science curriculum.
Home-page: https://scienceworld.github.io
Author: Peter Jansen
Classifier: Programming Language :: Python :: 3
Classifier: License :: OSI Approved :: Apache Software License
Classifier: Operating System :: POSIX :: Linux
Classifier: Operating System :: MacOS :: MacOS X
Requires-Python: >=3.7
License-File: LICENSE
Requires-Dist: py4j
Provides-Extra: webserver
Requires-Dist: py4j; extra == "webserver"
Requires-Dist: pywebio; extra == "webserver"
